pywhipper/__init__.py
pywhipper/core.py
pywhipper-0.1.0.dist-info/licenses/LICENSE
pywhipper-0.1.0.dist-info/METADATA
pywhipper-0.1.0.dist-info/WHEEL
pywhipper-0.1.0.dist-info/top_level.txt
pywhipper-0.1.0.dist-info/RECORD
