Metadata-Version: 2.4
Name: pywhipper
Version: 0.1.0
Summary: Line-by-line Python code profiler with optional memory tracking.
Home-page: https://github.com/soorajInsights/pywhipper
Author: Sooraj KK
Author-email: soorajkknmd@gmail.com
License: MIT
Classifier: Programming Language :: Python :: 3
Classifier: License :: OSI Approved :: MIT License
Classifier: Operating System :: OS Independent
Classifier: Development Status :: 3 - Alpha
Classifier: Intended Audience :: Developers
Classifier: Topic :: Software Development :: Debuggers
Classifier: Topic :: Software Development :: Libraries :: Python Modules
Requires-Python: >=3.8
License-File: LICENSE
Dynamic: license-file
